[
    {
        "id":1,
        "title":"Planta",
        "description":"Esta es una descripcion",
        "code":"LEAF",
        "price":100,
        "status":true,
        "stock":2,
        "category":"Ropa",
        "thumbnail":"https://dodo.ac/np/images/a/af/Leaf_NH_Icon.png"},
    {
        "id":2,
        "title":"Lampara Helado",
        "description":"Esta es una descripcion",
        "code":"SSL",
        "price":3000,
        "status":true,
        "stock":1,
        "category":"Decoracion",
        "thumbnail":"https://dodo.ac/np/images/7/78/Soft-Serve_Lamp_%28Vanilla%29_NH_Icon.png"},
    {
        "id":3,
        "title":"Guitarra",
        "description":"Esta es una descripcion",
        "code":"AGTR",
        "price":3210,
        "status":true,
        "stock":1,
        "category":"Decoracion",
        "thumbnail":"https://dodo.ac/np/images/4/42/Acoustic_Guitar_%28Natural%29_NH_Icon.png"},
    {
        "id":4,
        "title":"Monstruo",
        "description":"Esta es una descripcion",
        "code":"MS",
        "price":25000,
        "status":true,
        "stock":20,
        "category":"Decoracion",
        "thumbnail":"https://dodo.ac/np/images/d/d9/Monster_Statue_%28Brown%29_NH_Icon.png"},
    {
        "id":5,
        "title":"Reloj",
        "description":"Esta es una descripcion",
        "code":"AC",
        "price":44000,
        "status":true,
        "stock":12,
        "category":"Decoracion",
        "thumbnail":"https://dodo.ac/np/images/b/b4/Antique_Clock_%28Brown%29_NH_Icon.png"},
    {
        "id":6,
        "title":"Lavadora",
        "description":"Esta es una descripcion",
        "code":"AW",
        "price":4500,
        "status":true,
        "stock":5,
        "category":"Electrodomesticos",
        "thumbnail":"https://dodo.ac/np/images/f/fd/Automatic_Washer_%28White%29_NH_Icon.png"},
    {
        "id":7,
        "title":"Pintura Academica",
        "description":"Esta es una descripcion",
        "code":"AAC",
        "price":4980,
        "status":true,
        "stock":1,
        "category":"Decoracion",
        "thumbnail":"https://dodo.ac/np/images/f/f6/Academic_Painting_NH_Texture.png"},
    {
        "id":8,
        "title":"Bamboo",
        "description":"Esta es una descripcion",
        "code":"OBG",
        "price":3080,
        "status":true,
        "stock":1,
        "category":"Decoracion",
        "thumbnail":"https://dodo.ac/np/images/b/b7/Bamboo_Grass_NH_Icon.png"},
    {
        "id":9,
        "title":"Pintura",
        "description":"Esta es una descripcion",
        "code":"ADP",
        "price":4980,
        "status":true,
        "stock":1,
        "category":"Decoracion",
        "thumbnail":"https://dodo.ac/np/images/7/78/Dynamic_Painting_NH_Texture.png"},
    {
        "id":10,
        "title":"Silla",
        "description":"Esta es una descripcion",
        "code":"FSC",
        "price":1700,
        "status":true,
        "stock":1,
        "category":"Decoracion",
        "thumbnail":"https://dodo.ac/np/images/5/58/Study_Chair_%28Natural_-_Yellow%29_NH_Icon.png"}
]